logzai_otlp/__init__.py
logzai_otlp/__init__.pyi
logzai_otlp/main.py
logzai_otlp/models.py
logzai_otlp/plugins/__init__.py
logzai_otlp/plugins/fastapi.py
logzai_otlp/plugins/langchain.py
logzai_otlp/plugins/pydantic_ai.py
logzai_otlp-1.0.13.dist-info/licenses/LICENSE
logzai_otlp-1.0.13.dist-info/METADATA
logzai_otlp-1.0.13.dist-info/WHEEL
logzai_otlp-1.0.13.dist-info/top_level.txt
logzai_otlp-1.0.13.dist-info/RECORD
