Metadata-Version: 2.4
Name: logzai-otlp
Version: 1.0.13
Summary: OpenTelemetry logging client for LogzAI
Author: LogzAI
License: MIT
Project-URL: Homepage, https://logzai.com
Classifier: Programming Language :: Python :: 3
Classifier: License :: OSI Approved :: MIT License
Classifier: Operating System :: OS Independent
Requires-Python: >=3.9
License-File: LICENSE
Requires-Dist: opentelemetry-sdk>=1.27.0
Requires-Dist: opentelemetry-exporter-otlp>=1.27.0
Requires-Dist: python-dotenv>=1.0.0
Dynamic: license-file
